async_westjr/__init__.py
async_westjr/api.py
async_westjr/const.py
async_westjr/response_types/__init__.py
async_westjr/response_types/area_maintenance.py
async_westjr/response_types/area_master.py
async_westjr/response_types/stations.py
async_westjr/response_types/train_info.py
async_westjr/response_types/train_monitor_info.py
async_westjr/response_types/train_pos.py
async_westjr-0.4.dist-info/LICENSE
async_westjr-0.4.dist-info/METADATA
async_westjr-0.4.dist-info/WHEEL
async_westjr-0.4.dist-info/top_level.txt
async_westjr-0.4.dist-info/RECORD
