Metadata-Version: 2.1
Name: async-westjr
Version: 0.4
Summary: Handling of train operation information of JR West, a railroad company in Japan
Home-page: https://github.com/midorichaan/async-westjr
Author: midorichan
Author-email: midorichan@midorichan.net
License: Unlicense
Keywords: asyncwestjr
Classifier: License :: OSI Approved :: MIT License
Classifier: Programming Language :: Python
Classifier: Programming Language :: Python :: 3
Classifier: Programming Language :: Python :: 3 :: Only
Classifier: Programming Language :: Python :: Implementation :: CPython
Requires-Python: >=3.7
License-File: LICENSE
Requires-Dist: pydantic (>=1.10.4)
Requires-Dist: aiohttp (>=3.8.4)
Requires-Dist: types-requests (>=2.27.11)
Requires-Dist: typing-extensions (>=4.2.0)
Provides-Extra: dev
Requires-Dist: black ; extra == 'dev'
Requires-Dist: flake8 ; extra == 'dev'
Requires-Dist: isort ; extra == 'dev'
Requires-Dist: mypy ; extra == 'dev'
Requires-Dist: pre-commit ; extra == 'dev'
Requires-Dist: pytest ; extra == 'dev'
Requires-Dist: setuptools (>=46.4.0) ; extra == 'dev'
Requires-Dist: types-setuptools ; extra == 'dev'
Requires-Dist: wheel ; extra == 'dev'
